pycyrest/__init__.py
pycyrest/base.py
PyCyRest-1.0.1.dist-info/METADATA
PyCyRest-1.0.1.dist-info/WHEEL
PyCyRest-1.0.1.dist-info/top_level.txt
PyCyRest-1.0.1.dist-info/RECORD
