Metadata-Version: 2.1
Name: PyCyRest
Version: 1.0.1
Summary: A python CyREST library for Cytoscape.
Home-page: https://github.com/zachary822/PyCyRest
Author: Zachary Juang
Author-email: zacharyjuang@gmail.com
License: UNKNOWN
Platform: UNKNOWN
Classifier: License :: OSI Approved :: MIT License
Classifier: Programming Language :: Python :: 3.7
Requires-Dist: requests
Requires-Dist: lxml
